DSErrorsGenerator
