Metadata-Version: 1.0
Name: DSErrorsGenerator
Version: 0.0.3
Summary: Generate embeds with texts of your personal errors.
Home-page: https://github.com/FeeFort/discord-error-generator
Author: FeeFort
Author-email: bikov22022006@gmail.com
License: UNKNOWN
Platform: UNKNOWN
